temporal_normalization/__init__.py
temporal_normalization/index.py
temporal_normalization/commons/__init__.py
temporal_normalization/commons/print_utils.py
temporal_normalization/commons/temporal_models.py
temporal_normalization/commons/temporal_types.py
temporal_normalization/libs/temporal-normalization-2.1.0.jar
temporal_normalization/process/__init__.py
temporal_normalization/process/java_process.py
temporal_normalization_spacy-2.1.0.dist-info/licenses/LICENSE
temporal_normalization_spacy-2.1.0.dist-info/METADATA
temporal_normalization_spacy-2.1.0.dist-info/WHEEL
temporal_normalization_spacy-2.1.0.dist-info/top_level.txt
temporal_normalization_spacy-2.1.0.dist-info/RECORD
