Metadata-Version: 2.4
Name: temporal_normalization_spacy
Version: 2.1.0
Summary: A spaCy plugin for identifying and parsing historical data in Romanian texts
Home-page: https://github.com/iliedorobat/timespan-normalization-spacy
Author: Ilie Cristian Dorobat
Classifier: Programming Language :: Python :: 3
Classifier: License :: OSI Approved :: MIT License
Classifier: Operating System :: OS Independent
Requires-Python: >=3.6
License-File: LICENSE
Requires-Dist: spacy>=3.0
Requires-Dist: py4j
Requires-Dist: langdetect
Dynamic: author
Dynamic: classifier
Dynamic: description
Dynamic: description-content-type
Dynamic: home-page
Dynamic: license-file
Dynamic: requires-dist
Dynamic: requires-python
Dynamic: summary
